listset/__init__.py
listset-0.1.0.dist-info/LICENSE.txt
listset-0.1.0.dist-info/METADATA
listset-0.1.0.dist-info/RECORD
listset-0.1.0.dist-info/WHEEL
listset-0.1.0.dist-info/top_level.txt
